shiftdata/__init__.py
shiftdata/__main__.py
shiftdata/_shift.py
shiftdata/cli.py
shiftdata/py.typed
shift_forex_tester_data-0.1.3.dist-info/LICENSE
shift_forex_tester_data-0.1.3.dist-info/METADATA
shift_forex_tester_data-0.1.3.dist-info/WHEEL
shift_forex_tester_data-0.1.3.dist-info/entry_points.txt
shift_forex_tester_data-0.1.3.dist-info/top_level.txt
shift_forex_tester_data-0.1.3.dist-info/RECORD
