Metadata-Version: 2.1
Name: shift-forex-tester-data
Version: 0.1.3
Project-URL: Homepage, https://github.com/bachew/shift-forex-tester-data
Project-URL: Repository, https://github.com/bachew/shift-forex-tester-data
Requires-Python: >=3.9
License-File: LICENSE
Requires-Dist: attrs
Requires-Dist: click
Requires-Dist: python-dateutil
